{
  "notes": [
    {
      "id": "1",
      "content": "HTML is easy",
      "important": false
    },
    {
      "id": "2",
      "content": "Browser can execute only JavaScript",
      "important": true
    },
    {
      "id": "3",
      "content": "GET and POST are the most important methods of HTTP protocol",
      "important": true
    },
    {
      "id": "9b68",
      "content": "POST is used to create a new object",
      "important": false
    },
    {
      "id": "ac00",
      "content": "A new note",
      "important": false
    },
    {
      "id": "8b0d",
      "content": "And another note",
      "important": true
    }
  ]
}